bittrade_binance_websocket/__init__.py
bittrade_binance_websocket/channels/__init__.py
bittrade_binance_websocket/channels/book_ticker.py
bittrade_binance_websocket/channels/depth.py
bittrade_binance_websocket/channels/message.py
bittrade_binance_websocket/channels/open_orders.py
bittrade_binance_websocket/channels/subscribe.py
bittrade_binance_websocket/connection/__init__.py
bittrade_binance_websocket/connection/connection_operators.py
bittrade_binance_websocket/connection/generic.py
bittrade_binance_websocket/connection/http.py
bittrade_binance_websocket/connection/private.py
bittrade_binance_websocket/connection/private_user_stream.py
bittrade_binance_websocket/connection/public_stream.py
bittrade_binance_websocket/connection/reconnect.py
bittrade_binance_websocket/events/__init__.py
bittrade_binance_websocket/events/account_status.py
bittrade_binance_websocket/events/add_order.py
bittrade_binance_websocket/events/cancel_order.py
bittrade_binance_websocket/events/ping.py
bittrade_binance_websocket/events/request_response.py
bittrade_binance_websocket/events/time.py
bittrade_binance_websocket/framework/__init__.py
bittrade_binance_websocket/framework/framework.py
bittrade_binance_websocket/messages/__init__.py
bittrade_binance_websocket/messages/filters/__init__.py
bittrade_binance_websocket/messages/filters/kind.py
bittrade_binance_websocket/messages/heartbeat.py
bittrade_binance_websocket/messages/json.py
bittrade_binance_websocket/messages/listen.py
bittrade_binance_websocket/models/__init__.py
bittrade_binance_websocket/models/accounts.py
bittrade_binance_websocket/models/contingency_type.py
bittrade_binance_websocket/models/endpoints.py
bittrade_binance_websocket/models/enhanced_websocket.py
bittrade_binance_websocket/models/framework.py
bittrade_binance_websocket/models/loan.py
bittrade_binance_websocket/models/message.py
bittrade_binance_websocket/models/oco_list_status.py
bittrade_binance_websocket/models/order.py
bittrade_binance_websocket-0.4.8.dist-info/WHEEL
bittrade_binance_websocket-0.4.8.dist-info/METADATA
bittrade_binance_websocket-0.4.8.dist-info/RECORD
